test/__init__.py
test/packageTest.py
make_auto_venv-1.0.0.dist-info/METADATA
make_auto_venv-1.0.0.dist-info/WHEEL
make_auto_venv-1.0.0.dist-info/top_level.txt
make_auto_venv-1.0.0.dist-info/RECORD
